Workbook

Sheet 报关资料录入
B2: 报关信息
B3: 报关员: | F3: 申报日期： | G3: 46115 | H3: 申报单位:
B4: 公 司 资 料 | C4: 境内发货人 | E4: 深圳市沐星科技有限公司 | G4: 境外收货人 | H4: HONG KONG HENGSHUO INTELLIGENT TECHNOLOGY CO., LIMITED
C5: 统一社会代码 | E5: 91440300MA5F74BQ1L | G5: 地址 | H5: WORKSHOP 60, 3/F, BLOCK A, EAST SUN INDUSTRIAL CENTRE NO.16, SHING YIP STREET KL
C6: 海关编码 | E6: 91440300MA5F74BQ1L | G6: 电话/传真
C7: 地址 | E7: 深圳市龙岗区龙城街道黄阁坑社区吉祥里豪庭9栋铭德大厦A、B栋A座1010 | G7: 生产销售单位
C8: 电话/传真 | G8: 统一社会代码
B9: 海 关 资 料 | C9: 出境关别 | G9: 监管方式 | H9: 一般贸易 | J9: 合同协议号 | K9: HS-US-20260312
C10: 离境口岸 | G10: 征免性质 | H10: 一般征税 | J10: 合同日期 | K10: =G3-22 -> 46093
C11: 抵运国 | E11: 美国 | G11: 征免方式 | H11: 照章征税 | J11: 合同地点 | K11: 深圳
C12: 指运港 | G12: 备案号 | J12: 境内货源地 | K12: 深圳特区
C13: 贸易国 | E13: 香港 | G13: 许可证号 | J13: 原产国 | K13: 中国
C14: 运输方式 | E14: 水路运输 | G14: 包装类型 | H14: 纸制或纤维板制盒/箱 | J14: 成交方式 | K14: FOB
C15: 运输工具 | G15: 随附单证 | J15: 外汇币种 | K15: USD
C16: 提运单号 | G16: 箱唛 | H16: N/M | J16: 备注 | K16: 退税
C17: 集装箱号
B19: 货物信息
B20: 项号 | C20: 海关商品编码 | E20: 商品名称 | G20: 件数 | H20: 毛重 KG | I20: 净重 KG | J20: 数量 | K20: 单位 | L20: 单价
B21: 1 | G21: 1 | H21: =G21*1 -> 1 | I21: =H21-G21 -> 0 | J21: =G21*1 -> 1 | K21: 个
B23: 2 | G23: 1 | H23: =G23*1 -> 1 | I23: =H23-G23 -> 0 | J23: =G23*1 -> 1 | K23: 个
B25: 3 | G25: 1 | H25: =G25*1 -> 1 | I25: =H25-G25 -> 0 | J25: =G25*1 -> 1 | K25: 个
B27: 4 | G27: 1 | H27: =G27*1 -> 1 | I27: =H27-G27 -> 0 | J27: =G27*1 -> 1 | K27: 个
B29: 5 | G29: 1 | H29: =G29*1 -> 1 | I29: =H29-G29 -> 0 | J29: =G29*1 -> 1 | K29: 个
B31: 6 | G31: 1 | H31: =G31*1 -> 1 | I31: =H31-G31 -> 0 | J31: =G31*1 -> 1 | K31: 个
B33: 7 | G33: 1 | H33: =G33*1 -> 1 | I33: =H33-G33 -> 0 | J33: =G33*1 -> 1 | K33: 个
B35: 8 | G35: 1 | H35: =G35*1 -> 1 | I35: =H35-G35 -> 0 | J35: =G35*1 -> 1 | K35: 个
B37: 9 | G37: 1 | H37: =G37*1 -> 1 | I37: =H37-G37 -> 0 | J37: =G37*1 -> 1 | K37: 个
B39: 10 | G39: 1 | H39: =G39*1 -> 1 | I39: =H39-G39 -> 0 | J39: =G39*1 -> 1 | K39: 个
B41: 11 | G41: 1 | H41: =G41*1 -> 1 | I41: =H41-G41 -> 0 | J41: =G41*1 -> 1 | K41: 个
B43: 12 | G43: 1 | H43: =G43*1 -> 1 | I43: =H43-G43 -> 0 | J43: =G43*1 -> 1 | K43: 个
... B79: 30 | G79: 1 | H79: =G79*1 -> 1 | I79: =H79-G79 -> 0 | J79: =G79*1 -> 1 | K79: 个

Sheet 报关单
B2: 中华人民共和国海关出口货物报关单
B3: 预录入编号： | G3: 海关编号： | L3: =G5 -> 0 | P3: 页码/页数： | R3: 1/2
B4: 境内发货人 | D4: =报关资料录入!E5 -> 91440300MA5F74BQ1L | G4: 出境关别 | H4: =报关资料录入!F9 -> 0 | J4: 出口日期 | M4: 申报日期 | O4: 备案号
B5: =报关资料录入!E4 -> 深圳市沐星科技有限公司 | G5: =报关资料录入!E9 -> 0 | M5: =报关资料录入!G3 -> 46115 | O5: =报关资料录入!H12 -> 0
B6: 境外收货人 | D6: =报关资料录入!K4 -> 0 | G6: 运输方式 | J6: 运输工具名称/及航次号 | M6: 提运单号
B7: =报关资料录入!H4 -> HONG KONG HENGSHUO INTELLIGENT TECHNOLOGY CO., LIMITED | G7: =报关资料录入!E14 -> 水路运输 | J7: =报关资料录入!E15 -> 0 | M7: =报关资料录入!E16 -> 0
B8: 生产销售单位 | D8: =报关资料录入!H8 -> 0 | G8: 监管方式 | J8: 征免性质 | M8: 许可证号
B9: =报关资料录入!H7 -> 0 | G9: =报关资料录入!H9 -> 一般贸易 | J9: =报关资料录入!H10 -> 一般征税 | M9: =报关资料录入!H13 -> 0
B10: 合同协议号 | G10: 贸易国(地区) | J10: 运抵国(地区) | M10: 指运港 | O10: 离境口岸
B11: =报关资料录入!K9 -> HS-US-20260312 | G11: =报关资料录入!E13 -> 香港 | J11: =报关资料录入!E11 -> 美国 | M11: =报关资料录入!E12 -> 0 | O11: =报关资料录入!E10 -> 0
B12: 包装种类 | G12: 件数 | H12: 毛重 | J12: 净重 | L12: 成交方式 | M12: 运费 | O12: 保费 | Q12: 杂费
B13: =报关资料录入!H14 -> 纸制或纤维板制盒/箱 | G13: =装箱单!E77 -> 30 | H13: =装箱单!H77 -> 30 | J13: =装箱单!I77 -> 0 | L13: =报关资料录入!K14 -> FOB
B14: 随附单证及编号
B15: =报关资料录入!H15 -> 0
B16: 标记唛码及备注
B17: 备注: | C17: ="合计:"&发票!I45&发票!J45 -> 合计:USD0 | F17: =报关资料录入!H16 -> N/M | G17: =IF(报关资料录入!F17>0,"集装箱标箱号及号码: "&报关资料录入!E17&";"&报关资料录入!F17&";","") | M17: =报关资料录入!K16 -> 退税
B19: 项号 | C19: 商品编号 | E19: 商品名称及规格型号 | H19: 数量及单位 | K19: 单价/总价/币制 | M19: 原产国(地区) | N19: 最终目的国(地区) | P19: 境内货源地 | R19: 征免
B20: =报关资料录入!B21 -> 1 | C20: =报关资料录入!C21 -> 0 | E20: =报关资料录入!E21 -> 0 | H20: =报关资料录入!J21 -> 1 | J20: =报关资料录入!K21 -> 个 | K20: =报关资料录入!L21 -> 0 | M20: =报关资料录入!K13 -> 中国 | N20: =报关资料录入!E11 -> 美国 | P20: =报关资料录入!K12 -> 深圳特区 | R20: =报关资料录入!H11 -> 照章征税
E21: =报关资料录入!E22 -> 0 | H21: =报关资料录入!J22 -> 0 | J21: =报关资料录入!K22 -> 0 | K21: =H20*K20 -> 0
K22: =IF(报关资料录入!K15="HKD","港币 ",IF(报关资料录入!K15="USD","美元 ","人民币 ")) -> 美元
B23: =报关资料录入!B23 -> 2 | C23: =报关资料录入!C23 -> 0 | E23: =报关资料录入!E23 -> 0 | H23: =报关资料录入!J23 -> 1 | J23: =报关资料录入!K23 -> 个 | K23: =报关资料录入!L23 -> 0 | M23: =IF(B23=2,M20,"") -> 中国 | N23: =N20 -> 美国 | P23: =IF(B23=2,P20,"") -> 深圳特区 | R23: =IF(B23=2,R20,"") -> 照章征税
E24: =报关资料录入!E24 -> 0 | H24: =报关资料录入!J24 -> 0 | J24: =报关资料录入!K24 -> 0 | K24: =K23*H23 -> 0
K25: =IF(B23=2,K22,"") -> 美元
B26: =报关资料录入!B25 -> 3 | C26: =报关资料录入!C25 -> 0 | E26: =报关资料录入!E25 -> 0 | H26: =报关资料录入!J25 -> 1 | J26: =报关资料录入!K25 -> 个 | K26: =报关资料录入!L25 -> 0 | M26: 中国 | N26: =N23 -> 美国 | P26: 深圳特区 | R26: 照章征税
E27: =报关资料录入!E26 -> 0 | K27: =K26*H26 -> 0
K28: =IF(B23=2,K22,"") -> 美元
B29: =报关资料录入!B27 -> 4 | C29: =报关资料录入!C27 -> 0 | E29: =报关资料录入!E27 -> 0 | H29: =报关资料录入!J27 -> 1 | J29: =报关资料录入!K27 -> 个 | K29: =报关资料录入!L27 -> 0 | M29: 中国 | N29: =N26 -> 美国 | P29: 深圳特区 | R29: 照章征税
E30: =报关资料录入!E28 -> 0 | K30: =K29*H29 -> 0
K31: =IF(B23=2,K22,"") -> 美元
B32: =报关资料录入!B29 -> 5 | C32: =报关资料录入!C29 -> 0 | E32: =报关资料录入!E29 -> 0 | H32: =报关资料录入!J29 -> 1 | J32: =报关资料录入!K29 -> 个 | K32: =报关资料录入!L29 -> 0 | M32: 中国 | N32: =N29 -> 美国 | P32: 深圳特区 | R32: 照章征税
E33: =报关资料录入!E30 -> 0 | H33: =报关资料录入!J30 -> 0 | J33: =报关资料录入!K30 -> 0 | K33: =K32*H32 -> 0
K34: =IF(B23=2,K22,"") -> 美元
B35: =报关资料录入!B31 -> 6 | C35: =报关资料录入!C31 -> 0 | E35: =报关资料录入!E31 -> 0 | H35: =报关资料录入!J31 -> 1 | J35: =报关资料录入!K31 -> 个 | K35: =报关资料录入!L31 -> 0 | M35: 中国 | N35: =N32 -> 美国 | P35: 深圳特区 | R35: 照章征税
E36: =报关资料录入!E32 -> 0 | H36: =报关资料录入!J32 -> 0 | J36: =报关资料录入!K32 -> 0 | K36: =H35*K35 -> 0
K37: 美元
B38: =报关资料录入!B33 -> 7 | C38: =报关资料录入!C33 -> 0 | E38: =报关资料录入!E33 -> 0 | H38: =报关资料录入!J33 -> 1 | J38: =报关资料录入!K33 -> 个 | K38: =报关资料录入!L33 -> 0 | M38: 中国 | N38: =N35 -> 美国 | P38: 深圳特区 | R38: 照章征税
E39: =报关资料录入!E34 -> 0 | H39: =报关资料录入!J40 -> 0 | J39: =报关资料录入!K40 -> 0 | K39: =H38*K38 -> 0
K40: 美元
B41: =报关资料录入!B35 -> 8 | C41: =报关资料录入!C35 -> 0 | E41: =报关资料录入!E35 -> 0 | H41: =报关资料录入!J35 -> 1 | J41: =报关资料录入!K35 -> 个 | K41: =报关资料录入!L35 -> 0 | M41: 中国 | N41: =N38 -> 美国 | P41: 深圳特区 | R41: 照章征税
E42: =报关资料录入!E36 -> 0 | H42: =报关资料录入!J42 -> 0 | J42: =报关资料录入!K42 -> 0 | K42: =K41*H41 -> 0
K43: 美元
B44: =报关资料录入!B37 -> 9 | C44: =报关资料录入!C37 -> 0 | E44: =报关资料录入!E37 -> 0 | H44: =报关资料录入!J37 -> 1 | J44: =报关资料录入!K37 -> 个 | K44: =报关资料录入!L37 -> 0 | M44: 中国 | N44: =N41 -> 美国 | P44: 深圳特区 | R44: 照章征税
E45: =报关资料录入!E38 -> 0 | K45: =K44*H44 -> 0
K46: 美元
B47: =报关资料录入!B39 -> 10 | C47: =报关资料录入!C39 -> 0 | E47: =报关资料录入!E39 -> 0 | H47: =报关资料录入!J39 -> 1 | J47: =报关资料录入!K39 -> 个 | K47: =报关资料录入!L39 -> 0 | M47: 中国 | N47: =N44 -> 美国 | P47: 深圳特区 | R47: 照章征税
E48: =报关资料录入!E40 -> 0 | K48: =K47*H47 -> 0
K49: 美元
B50: =报关资料录入!B41 -> 11 | C50: =报关资料录入!C41 -> 0 | E50: =报关资料录入!E41 -> 0 | H50: =报关资料录入!J41 -> 1 | J50: =报关资料录入!K41 -> 个 | K50: =报关资料录入!L41 -> 0 | M50: 中国 | N50: =N47 -> 美国 | P50: 深圳特区 | R50: 照章征税
E51: =报关资料录入!E42 -> 0 | H51: =报关资料录入!J48 -> 0 | J51: =报关资料录入!K48 -> 0 | K51: =K50*H50 -> 0
K52: 美元
B53: =报关资料录入!B43 -> 12 | C53: =报关资料录入!C43 -> 0 | E53: =报关资料录入!E43 -> 0 | H53: =报关资料录入!J43 -> 1 | J53: =报关资料录入!K43 -> 个 | K53: =报关资料录入!L43 -> 0 | M53: 中国 | N53: =N50 -> 美国 | P53: 深圳特区 | R53: 照章征税
E54: =报关资料录入!E44 -> 0 | H54: =报关资料录入!J66 -> 0 | J54: =报关资料录入!K66 -> 0 | K54: =H53*K53 -> 0
K55: 美元
B56: =报关资料录入!B45 -> 13 | C56: =报关资料录入!C45 -> 0 | E56: =报关资料录入!E45 -> 0 | H56: =报关资料录入!J45 -> 1 | J56: =报关资料录入!K45 -> 个 | K56: =报关资料录入!L45 -> 0 | M56: 中国 | N56: =N53 -> 美国 | P56: 深圳特区 | R56: 照章征税
E57: =报关资料录入!E46 -> 0 | H57: =报关资料录入!J40 -> 0 | J57: =报关资料录入!K40 -> 0 | K57: =H56*K56 -> 0
K58: 美元
B59: =报关资料录入!B47 -> 14 | C59: =报关资料录入!C47 -> 0 | E59: =报关资料录入!E47 -> 0 | H59: =报关资料录入!J47 -> 1 | J59: =报关资料录入!K47 -> 个 | K59: =报关资料录入!L47 -> 0 | M59: 中国 | N59: =N56 -> 美国 | P59: 深圳特区 | R59: 照章征税
E60: =报关资料录入!E48 -> 0 | H60: =报关资料录入!J42 -> 0 | J60: =报关资料录入!K42 -> 0 | K60: =K59*H59 -> 0
K61: 美元
B62: =报关资料录入!B49 -> 15 | C62: =报关资料录入!C49 -> 0 | E62: =报关资料录入!E49 -> 0 | H62: =报关资料录入!J49 -> 1 | J62: =报关资料录入!K49 -> 个 | K62: =报关资料录入!L49 -> 0 | M62: 中国 | N62: =N59 -> 美国 | P62: 深圳特区 | R62: 照章征税
E63: =报关资料录入!E50 -> 0 | K63: =K62*H62 -> 0
K64: 美元
B65: =报关资料录入!B51 -> 16 | C65: =报关资料录入!C51 -> 0 | E65: =报关资料录入!E51 -> 0 | H65: =报关资料录入!J51 -> 1 | J65: =报关资料录入!K51 -> 个 | K65: =报关资料录入!L51 -> 0 | M65: 中国 | N65: =N62 -> 美国 | P65: 深圳特区 | R65: 照章征税
E66: =报关资料录入!E52 -> 0 | H66: =报关资料录入!J48 -> 0 | J66: =报关资料录入!K48 -> 0 | K66: =K65*H65 -> 0
K67: 美元
B68: =报关资料录入!B53 -> 17 | C68: =报关资料录入!C53 -> 0 | E68: =报关资料录入!E53 -> 0 | H68: =报关资料录入!J53 -> 1 | J68: =报关资料录入!K53 -> 个 | K68: =报关资料录入!L53 -> 0 | M68: 中国 | N68: =N65 -> 美国 | P68: 深圳特区 | R68: 照章征税
E69: =报关资料录入!E54 -> 0 | K69: =K68*H68 -> 0
K70: 美元
B71: =报关资料录入!B55 -> 18 | C71: =报关资料录入!C55 -> 0 | E71: =报关资料录入!E55 -> 0 | H71: =报关资料录入!J55 -> 1 | J71: =报关资料录入!K55 -> 个 | K71: =报关资料录入!L55 -> 0 | M71: 中国 | N71: =N68 -> 美国 | P71: 深圳特区 | R71: 照章征税
E72: =报关资料录入!E56 -> 0 | J72: =报关资料录入!K54 -> 0 | K72: =K71*H71 -> 0
K73: 美元
B74: =报关资料录入!B57 -> 19 | C74: =报关资料录入!C57 -> 0 | E74: =报关资料录入!E57 -> 0 | H74: =报关资料录入!J57 -> 1 | J74: =报关资料录入!K57 -> 个 | K74: =报关资料录入!L57 -> 0 | M74: 中国 | N74: =N71 -> 美国 | P74: 深圳特区 | R74: 照章征税
E75: =报关资料录入!E58 -> 0 | K75: =K74*H74 -> 0
K76: 美元
B77: =报关资料录入!B59 -> 20 | C77: =报关资料录入!C59 -> 0 | E77: =报关资料录入!E59 -> 0 | H77: =报关资料录入!J59 -> 1 | J77: =报关资料录入!K59 -> 个 | K77: =报关资料录入!L59 -> 0 | M77: 中国 | N77: =N74 -> 美国 | P77: 深圳特区 | R77: 照章征税
E78: =报关资料录入!E60 -> 0 | H78: =报关资料录入!J60 -> 0 | J78: =报关资料录入!K60 -> 0 | K78: =K77*H77 -> 0
K79: 美元
B80: =报关资料录入!B61 -> 21 | C80: =报关资料录入!C61 -> 0 | E80: =报关资料录入!E61 -> 0 | H80: =报关资料录入!J61 -> 1 | J80: =报关资料录入!K61 -> 个 | K80: =报关资料录入!L61 -> 0 | M80: 中国 | N80: =N77 -> 美国 | P80: 深圳特区 | R80: 照章征税
E81: =报关资料录入!E62 -> 0 | J81: =报关资料录入!K66 -> 0 | K81: =K80*H80 -> 0
K82: 美元
B83: =报关资料录入!B63 -> 22 | C83: =报关资料录入!C63 -> 0 | E83: =报关资料录入!E63 -> 0 | H83: =报关资料录入!J63 -> 1 | J83: =报关资料录入!K63 -> 个 | K83: =报关资料录入!L63 -> 0 | M83: 中国 | N83: =N80 -> 美国 | P83: 深圳特区 | R83: 照章征税
E84: =报关资料录入!E64 -> 0 | H84: =报关资料录入!J66 -> 0 | K84: =K83*H83 -> 0
K85: 美元
B86: =报关资料录入!B65 -> 23 | C86: =报关资料录入!C65 -> 0 | E86: =报关资料录入!E65 -> 0 | H86: =报关资料录入!J65 -> 1 | J86: =报关资料录入!K65 -> 个 | K86: =报关资料录入!L65 -> 0 | M86: 中国 | N86: =N83 -> 美国 | P86: 深圳特区 | R86: 照章征税
E87: =报关资料录入!E66 -> 0 | J87: =报关资料录入!K85 -> 0 | K87: =K86*H86 -> 0
K88: 美元
B89: =报关资料录入!B67 -> 24 | C89: =报关资料录入!C67 -> 0 | E89: =报关资料录入!E67 -> 0 | H89: =报关资料录入!J67 -> 1 | J89: =报关资料录入!K67 -> 个 | K89: =报关资料录入!L67 -> 0 | M89: 中国 | N89: =N86 -> 美国 | P89: 深圳特区 | R89: 照章征税
E90: =报关资料录入!E68 -> 0 | H90: =报关资料录入!J72 -> 0 | J90: =报关资料录入!K88 -> 0 | K90: =K89*H89 -> 0
K91: 美元
B92: =报关资料录入!B69 -> 25 | C92: =报关资料录入!C69 -> 0 | E92: =报关资料录入!E69 -> 0 | H92: =报关资料录入!J69 -> 1 | J92: =报关资料录入!K69 -> 个 | K92: =报关资料录入!L69 -> 0 | M92: 中国 | N92: =N89 -> 美国 | P92: 深圳特区 | R92: 照章征税
E93: =报关资料录入!E70 -> 0 | J93: =报关资料录入!K91 -> 0 | K93: =K92*H92 -> 0
K94: 美元
B95: =报关资料录入!B71 -> 26 | C95: =报关资料录入!C71 -> 0 | E95: =报关资料录入!E71 -> 0 | H95: =报关资料录入!J71 -> 1 | J95: =报关资料录入!K71 -> 个 | K95: =报关资料录入!L71 -> 0 | M95: 中国 | N95: =N92 -> 美国 | P95: 深圳特区 | R95: 照章征税
E96: =报关资料录入!E72 -> 0 | H96: =报关资料录入!J78 -> 0 | K96: =K95*H95 -> 0
K97: 美元
B98: =报关资料录入!B73 -> 27 | C98: =报关资料录入!C73 -> 0 | E98: =报关资料录入!E73 -> 0 | H98: =报关资料录入!J73 -> 1 | J98: =报关资料录入!K73 -> 个 | K98: =报关资料录入!L73 -> 0 | M98: 中国 | N98: =N95 -> 美国 | P98: 深圳特区 | R98: 照章征税
E99: =报关资料录入!E74 -> 0 | J99: =报关资料录入!K82 -> 0 | K99: =K98*H98 -> 0
K100: 美元
B101: =报关资料录入!B75 -> 28 | C101: =报关资料录入!C75 -> 0 | E101: =报关资料录入!E75 -> 0 | H101: =报关资料录入!J75 -> 1 | J101: =报关资料录入!K75 -> 个 | K101: =报关资料录入!L75 -> 0 | M101: 中国 | N101: =N98 -> 美国 | P101: 深圳特区 | R101: 照章征税
E102: =报关资料录入!E76 -> 0 | H102: =报关资料录入!J84 -> 0 | J102: =报关资料录入!K85 -> 0 | K102: =K101*H101 -> 0
...

Sheet 装箱单
B2: =报关资料录入!E4 -> 深圳市沐星科技有限公司
B3: ="地址:"&报关资料录入!E7 -> 地址:深圳市龙岗区龙城街道黄阁坑社区吉祥里豪庭9栋铭德大厦A、B栋A座1010
B5: 装 箱 单
B6: PACKING LIST
B7: 买方 Buyers : | D7: =报关资料录入!H4 -> HONG KONG HENGSHUO INTELLIGENT TECHNOLOGY CO., LIMITED | G7: 发票日期 Date : | I7: =报关资料录入!K10 -> 46093
B8: 地址 Address : | D8: =报关资料录入!H5 -> WORKSHOP 60, 3/F, BLOCK A, EAST SUN INDUSTRIAL CENTRE NO.16, SHING YIP STREET KL | G8: 发票编号 Invoice No : | I8: =报关资料录入!K9 -> HS-US-20260312
B10: 装运口岸及目的地 : | D10: ="由 "&报关资料录入!K11&" 至 "&报关资料录入!E11 -> 由 深圳 至 美国 | G10: 成交方式 : | I10: =报关资料录入!K14 -> FOB
B11: Loading Port & Destination : | H11: Terms of Payment :
B13: 项号 No. | C13: 商品名称及规格 Description of Goods | E13: 总箱数 Ge.Crate | F13: 总数量 Ge.Quantity | H13: 总毛重(千克) G.W.:KG | I13: 总净重(千克) N.W.:KG
B15: =报关资料录入!B21 -> 1 | C15: =报关资料录入!E21 -> 0 | E15: =报关资料录入!G21 -> 1 | F15: =报关资料录入!J21 -> 1 | G15: =报关资料录入!K21 -> 个 | H15: =报关资料录入!H21 -> 1 | I15: =报关资料录入!I21 -> 0
F16: =报关资料录入!J22 -> 0 | G16: =报关资料录入!K22 -> 0
B17: =报关资料录入!B23 -> 2 | C17: =报关资料录入!E23 -> 0 | E17: =报关资料录入!G23 -> 1 | F17: =报关资料录入!J23 -> 1 | G17: =报关资料录入!K23 -> 个 | H17: =报关资料录入!H23 -> 1 | I17: =报关资料录入!I23 -> 0
F18: =报关资料录入!J24 -> 0 | G18: =报关资料录入!K24 -> 0
B19: =报关资料录入!B25 -> 3 | C19: =报关资料录入!E25 -> 0 | E19: =报关资料录入!G25 -> 1 | F19: =报关资料录入!J25 -> 1 | G19: =报关资料录入!K25 -> 个 | H19: =报关资料录入!H25 -> 1 | I19: =报关资料录入!I25 -> 0
F20: =报关资料录入!J26 -> 0 | G20: =报关资料录入!K26 -> 0
B21: =报关资料录入!B27 -> 4 | C21: =报关资料录入!E27 -> 0 | E21: =报关资料录入!G27 -> 1 | F21: =报关资料录入!J27 -> 1 | G21: =报关资料录入!K27 -> 个 | H21: =报关资料录入!H27 -> 1 | I21: =报关资料录入!I27 -> 0
F22: =报关资料录入!J28 -> 0 | G22: =报关资料录入!K28 -> 0
B23: =报关资料录入!B29 -> 5 | C23: =报关资料录入!E29 -> 0 | E23: =报关资料录入!G29 -> 1 | F23: =报关资料录入!J29 -> 1 | G23: =报关资料录入!K29 -> 个 | H23: =报关资料录入!H29 -> 1 | I23: =报关资料录入!I29 -> 0
F24: =报关资料录入!J30 -> 0 | G24: =报关资料录入!K30 -> 0
B25: =报关资料录入!B31 -> 6 | C25: =报关资料录入!E31 -> 0 | E25: =报关资料录入!G31 -> 1 | F25: =报关资料录入!J31 -> 1 | G25: =报关资料录入!K31 -> 个 | H25: =报关资料录入!H31 -> 1 | I25: =报关资料录入!I31 -> 0
F26: =报关资料录入!J32 -> 0 | G26: =报关资料录入!K32 -> 0
B27: =报关资料录入!B33 -> 7 | C27: =报关资料录入!E33 -> 0 | E27: =报关资料录入!G33 -> 1 | F27: =报关资料录入!J33 -> 1 | G27: =报关资料录入!K33 -> 个 | H27: =报关资料录入!H33 -> 1 | I27: =报关资料录入!I33 -> 0
F28: =报关资料录入!J34 -> 0 | G28: =报关资料录入!K34 -> 0
B29: =报关资料录入!B35 -> 8 | C29: =报关资料录入!E35 -> 0 | E29: =报关资料录入!G35 -> 1 | F29: =报关资料录入!J35 -> 1 | G29: =报关资料录入!K35 -> 个 | H29: =报关资料录入!H35 -> 1 | I29: =报关资料录入!I35 -> 0
F30: =报关资料录入!J36 -> 0 | G30: =报关资料录入!K36 -> 0
B31: =报关资料录入!B37 -> 9 | C31: =报关资料录入!E37 -> 0 | E31: =报关资料录入!G37 -> 1 | F31: =报关资料录入!J37 -> 1 | G31: =报关资料录入!K37 -> 个 | H31: =报关资料录入!H37 -> 1 | I31: =报关资料录入!I37 -> 0
F32: =报关资料录入!J38 -> 0 | G32: =报关资料录入!K38 -> 0
B33: =报关资料录入!B39 -> 10 | C33: =报关资料录入!E39 -> 0 | E33: =报关资料录入!G39 -> 1 | F33: =报关资料录入!J39 -> 1 | G33: =报关资料录入!K39 -> 个 | H33: =报关资料录入!H39 -> 1 | I33: =报关资料录入!I39 -> 0
F34: =报关资料录入!J40 -> 0 | G34: =报关资料录入!K40 -> 0
B35: =报关资料录入!B41 -> 11 | C35: =报关资料录入!E41 -> 0 | E35: =报关资料录入!G41 -> 1 | F35: =报关资料录入!J41 -> 1 | G35: =报关资料录入!K41 -> 个 | H35: =报关资料录入!H41 -> 1 | I35: =报关资料录入!I41 -> 0
F36: =报关资料录入!J42 -> 0 | G36: =报关资料录入!K42 -> 0
B37: =报关资料录入!B43 -> 12 | C37: =报关资料录入!E43 -> 0 | E37: =报关资料录入!G43 -> 1 | F37: =报关资料录入!J43 -> 1 | G37: =报关资料录入!K43 -> 个 | H37: =报关资料录入!H43 -> 1 | I37: =报关资料录入!I43 -> 0
F38: =报关资料录入!J44 -> 0 | G38: =报关资料录入!K44 -> 0
B39: =报关资料录入!B45 -> 13 | C39: =报关资料录入!E45 -> 0 | E39: =报关资料录入!G45 -> 1 | F39: =报关资料录入!J45 -> 1 | G39: =报关资料录入!K45 -> 个 | H39: =报关资料录入!H45 -> 1 | I39: =报关资料录入!I45 -> 0
F40: =报关资料录入!J46 -> 0 | G40: =报关资料录入!K46 -> 0
B41: =报关资料录入!B47 -> 14 | C41: =报关资料录入!E47 -> 0 | E41: =报关资料录入!G47 -> 1 | F41: =报关资料录入!J47 -> 1 | G41: =报关资料录入!K47 -> 个 | H41: =报关资料录入!H47 -> 1 | I41: =报关资料录入!I47 -> 0
F42: =报关资料录入!J48 -> 0 | G42: =报关资料录入!K48 -> 0
B43: =报关资料录入!B49 -> 15 | C43: =报关资料录入!E49 -> 0 | E43: =报关资料录入!G49 -> 1 | F43: =报关资料录入!J49 -> 1 | G43: =报关资料录入!K49 -> 个 | H43: =报关资料录入!H49 -> 1 | I43: =报关资料录入!I49 -> 0
F44: =报关资料录入!J50 -> 0 | G44: =报关资料录入!K50 -> 0
B45: =报关资料录入!B51 -> 16 | C45: =报关资料录入!E51 -> 0 | E45: =报关资料录入!G51 -> 1 | F45: =报关资料录入!J51 -> 1 | G45: =报关资料录入!K51 -> 个 | H45: =报关资料录入!H51 -> 1 | I45: =报关资料录入!I51 -> 0
F46: =报关资料录入!J52 -> 0 | G46: =报关资料录入!K52 -> 0
B47: =报关资料录入!B53 -> 17 | C47: =报关资料录入!E53 -> 0 | E47: =报关资料录入!G53 -> 1 | F47: =报关资料录入!J53 -> 1 | G47: =报关资料录入!K53 -> 个 | H47: =报关资料录入!H53 -> 1 | I47: =报关资料录入!I53 -> 0
F48: =报关资料录入!J54 -> 0 | G48: =报关资料录入!K54 -> 0
B49: =报关资料录入!B55 -> 18 | C49: =报关资料录入!E55 -> 0 | E49: =报关资料录入!G55 -> 1 | F49: =报关资料录入!J55 -> 1 | G49: =报关资料录入!K55 -> 个 | H49: =报关资料录入!H55 -> 1 | I49: =报关资料录入!I55 -> 0
F50: =报关资料录入!J56 -> 0 | G50: =报关资料录入!K56 -> 0
B51: =报关资料录入!B57 -> 19 | C51: =报关资料录入!E57 -> 0 | E51: =报关资料录入!G57 -> 1 | F51: =报关资料录入!J57 -> 1 | G51: =报关资料录入!K57 -> 个 | H51: =报关资料录入!H57 -> 1 | I51: =报关资料录入!I57 -> 0
F52: =报关资料录入!J58 -> 0 | G52: =报关资料录入!K58 -> 0
B53: =报关资料录入!B59 -> 20 | C53: =报关资料录入!E59 -> 0 | E53: =报关资料录入!G59 -> 1 | F53: =报关资料录入!J59 -> 1 | G53: =报关资料录入!K59 -> 个 | H53: =报关资料录入!H59 -> 1 | I53: =报关资料录入!I59 -> 0
F54: =报关资料录入!J60 -> 0 | G54: =报关资料录入!K60 -> 0
B55: =报关资料录入!B61 -> 21 | C55: =报关资料录入!E61 -> 0 | E55: =报关资料录入!G61 -> 1 | F55: =报关资料录入!J61 -> 1 | G55: =报关资料录入!K61 -> 个 | H55: =报关资料录入!H61 -> 1 | I55: =报关资料录入!I61 -> 0
F56: =报关资料录入!J62 -> 0 | G56: =报关资料录入!K62 -> 0
B57: =报关资料录入!B63 -> 22 | C57: =报关资料录入!E63 -> 0 | E57: =报关资料录入!G63 -> 1 | F57: =报关资料录入!J63 -> 1 | G57: =报关资料录入!K63 -> 个 | H57: =报关资料录入!H63 -> 1 | I57: =报关资料录入!I63 -> 0
F58: =报关资料录入!J64 -> 0 | G58: =报关资料录入!K64 -> 0
B59: =报关资料录入!B65 -> 23 | C59: =报关资料录入!E65 -> 0 | E59: =报关资料录入!G65 -> 1 | F59: =报关资料录入!J65 -> 1 | G59: =报关资料录入!K65 -> 个 | H59: =报关资料录入!H65 -> 1 | I59: =报关资料录入!I65 -> 0
F60: =报关资料录入!J66 -> 0 | G60: =报关资料录入!K66 -> 0
B61: =报关资料录入!B67 -> 24 | C61: =报关资料录入!E67 -> 0 | E61: =报关资料录入!G67 -> 1 | F61: =报关资料录入!J67 -> 1 | G61: =报关资料录入!K67 -> 个 | H61: =报关资料录入!H67 -> 1 | I61: =报关资料录入!I67 -> 0
F62: =报关资料录入!J68 -> 0 | G62: =报关资料录入!K68 -> 0
B63: =报关资料录入!B69 -> 25 | C63: =报关资料录入!E69 -> 0 | E63: =报关资料录入!G69 -> 1 | F63: =报关资料录入!J69 -> 1 | G63: =报关资料录入!K69 -> 个 | H63: =报关资料录入!H69 -> 1 | I63: =报关资料录入!I69 -> 0
F64: =报关资料录入!J70 -> 0 | G64: =报关资料录入!K70 -> 0
B65: =报关资料录入!B71 -> 26 | C65: =报关资料录入!E71 -> 0 | E65: =报关资料录入!G71 -> 1 | F65: =报关资料录入!J71 -> 1 | G65: =报关资料录入!K71 -> 个 | H65: =报关资料录入!H71 -> 1 | I65: =报关资料录入!I71 -> 0
F66: =报关资料录入!J72 -> 0 | G66: =报关资料录入!K72 -> 0
B67: =报关资料录入!B73 -> 27 | C67: =报关资料录入!E73 -> 0 | E67: =报关资料录入!G73 -> 1 | F67: =报关资料录入!J73 -> 1 | G67: =报关资料录入!K73 -> 个 | H67: =报关资料录入!H73 -> 1 | I67: =报关资料录入!I73 -> 0
F68: =报关资料录入!J74 -> 0 | G68: =报关资料录入!K74 -> 0
B69: =报关资料录入!B75 -> 28 | C69: =报关资料录入!E75 -> 0 | E69: =报关资料录入!G75 -> 1 | F69: =报关资料录入!J75 -> 1 | G69: =报关资料录入!K75 -> 个 | H69: =报关资料录入!H75 -> 1 | I69: =报关资料录入!I75 -> 0
F70: =报关资料录入!J76 -> 0 | G70: =报关资料录入!K76 -> 0
B71: =报关资料录入!B77 -> 29 | C71: =报关资料录入!E77 -> 0 | E71: =报关资料录入!G77 -> 1 | F71: =报关资料录入!J77 -> 1 | G71: =报关资料录入!K77 -> 个 | H71: =报关资料录入!H77 -> 1 | I71: =报关资料录入!I77 -> 0
F72: =报关资料录入!J78 -> 0 | G72: =报关资料录入!K78 -> 0
B73: =报关资料录入!B79 -> 30 | C73: =报关资料录入!E79 -> 0 | E73: =报关资料录入!G79 -> 1 | F73: =报关资料录入!J79 -> 1 | G73: =报关资料录入!K75 -> 个 | H73: =报关资料录入!H79 -> 1 | I73: =报关资料录入!I79 -> 0
F74: =报关资料录入!J80 -> 0 | G74: =报关资料录入!K76 -> 0
B77: 合计 TOTAL: | E77: =SUM(E15:E73) -> 30 | H77: =SUM(H15:H73) -> 30 | I77: =SUM(I15:I73) -> 0
B79: 唛头 Marks:
B81: =报关资料录入!H16 -> N/M

Sheet 发票
B2: =报关资料录入!E4 -> 深圳市沐星科技有限公司
B3: ="地址:"&报关资料录入!E7 -> 地址:深圳市龙岗区龙城街道黄阁坑社区吉祥里豪庭9栋铭德大厦A、B栋A座1010
B5: 发 票
B6: INVOICE
B7: 买方 Buyers : | D7: =报关资料录入!H4 -> HONG KONG HENGSHUO INTELLIGENT TECHNOLOGY CO., LIMITED | G7: 发票日期 Date : | I7: =报关资料录入!G3 -> 46115
B8: 地址 Address : | D8: =报关资料录入!H5 -> WORKSHOP 60, 3/F, BLOCK A, EAST SUN INDUSTRIAL CENTRE NO.16, SHING YIP STREET KL | G8: 发票号 Invoice No : | I8: =报关资料录入!K9 -> HS-US-20260312
B10: 装运口岸及目的地 : | D10: =装箱单!D10 -> 由 深圳 至 美国 | G10: 成交方式 : | I10: =报关资料录入!K14 -> FOB
B11: Loading Port & Destination : | H11: Terms of Payment :
B13: 项号 No. | C13: 商品名称及规格 Description of Goods | F13: 数量/重量 Quantity/Weight | H13: 单价 Unit price | I13: 总金额 Amount
B15: =报关资料录入!B21 -> 1 | C15: =报关资料录入!E21 -> 0 | F15: =报关资料录入!J21 -> 1 | G15: =报关资料录入!K21 -> 个 | H15: =报关资料录入!L21 -> 0 | I15: =报关资料录入!K15 -> USD | J15: =H15*F15 -> 0
B16: =报关资料录入!B23 -> 2 | C16: =报关资料录入!E23 -> 0 | F16: =报关资料录入!J23 -> 1 | G16: =报关资料录入!K23 -> 个 | H16: =报关资料录入!L23 -> 0 | I16: USD | J16: =H16*F16 -> 0
B17: =报关资料录入!B25 -> 3 | C17: =报关资料录入!E25 -> 0 | F17: =报关资料录入!J25 -> 1 | G17: =报关资料录入!K25 -> 个 | H17: =报关资料录入!L25 -> 0 | I17: USD | J17: =H17*F17 -> 0
B18: =报关资料录入!B27 -> 4 | C18: =报关资料录入!E27 -> 0 | F18: =报关资料录入!J27 -> 1 | G18: =报关资料录入!K27 -> 个 | H18: =报关资料录入!L27 -> 0 | I18: USD | J18: =H18*F18 -> 0
B19: =报关资料录入!B29 -> 5 | C19: =报关资料录入!E29 -> 0 | F19: =报关资料录入!J29 -> 1 | G19: =报关资料录入!K29 -> 个 | H19: =报关资料录入!L29 -> 0 | I19: USD | J19: =H19*F19 -> 0
B20: =报关资料录入!B31 -> 6 | C20: =报关资料录入!E31 -> 0 | F20: =报关资料录入!J31 -> 1 | G20: =报关资料录入!K31 -> 个 | H20: =报关资料录入!L31 -> 0 | I20: USD | J20: =H20*F20 -> 0
B21: =报关资料录入!B33 -> 7 | C21: =报关资料录入!E33 -> 0 | F21: =报关资料录入!J33 -> 1 | G21: =报关资料录入!K33 -> 个 | H21: =报关资料录入!L33 -> 0 | I21: USD | J21: =H21*F21 -> 0
B22: =报关资料录入!B35 -> 8 | C22: =报关资料录入!E35 -> 0 | F22: =报关资料录入!J35 -> 1 | G22: =报关资料录入!K35 -> 个 | H22: =报关资料录入!L35 -> 0 | I22: USD | J22: =H22*F22 -> 0
B23: =报关资料录入!B37 -> 9 | C23: =报关资料录入!E37 -> 0 | F23: =报关资料录入!J37 -> 1 | G23: =报关资料录入!K37 -> 个 | H23: =报关资料录入!L37 -> 0 | I23: USD | J23: =H23*F23 -> 0
B24: =报关资料录入!B39 -> 10 | C24: =报关资料录入!E39 -> 0 | F24: =报关资料录入!J39 -> 1 | G24: =报关资料录入!K39 -> 个 | H24: =报关资料录入!L39 -> 0 | I24: USD | J24: =H24*F24 -> 0
B25: =报关资料录入!B41 -> 11 | C25: =报关资料录入!E41 -> 0 | F25: =报关资料录入!J41 -> 1 | G25: =报关资料录入!K41 -> 个 | H25: =报关资料录入!L41 -> 0 | I25: USD | J25: =H25*F25 -> 0
B26: =报关资料录入!B43 -> 12 | C26: =报关资料录入!E43 -> 0 | F26: =报关资料录入!J43 -> 1 | G26: =报关资料录入!K43 -> 个 | H26: =报关资料录入!L43 -> 0 | I26: USD | J26: =H26*F26 -> 0
B27: =报关资料录入!B45 -> 13 | C27: =报关资料录入!E45 -> 0 | F27: =报关资料录入!J45 -> 1 | G27: =报关资料录入!K45 -> 个 | H27: =报关资料录入!L45 -> 0 | I27: USD | J27: =H27*F27 -> 0
B28: =报关资料录入!B47 -> 14 | C28: =报关资料录入!E47 -> 0 | F28: =报关资料录入!J47 -> 1 | G28: =报关资料录入!K47 -> 个 | H28: =报关资料录入!L47 -> 0 | I28: USD | J28: =H28*F28 -> 0
B29: =报关资料录入!B49 -> 15 | C29: =报关资料录入!E49 -> 0 | F29: =报关资料录入!J49 -> 1 | G29: =报关资料录入!K49 -> 个 | H29: =报关资料录入!L49 -> 0 | I29: USD | J29: =H29*F29 -> 0
B30: =报关资料录入!B51 -> 16 | C30: =报关资料录入!E51 -> 0 | F30: =报关资料录入!J51 -> 1 | G30: =报关资料录入!K51 -> 个 | H30: =报关资料录入!L51 -> 0 | I30: USD | J30: =H30*F30 -> 0
B31: =报关资料录入!B53 -> 17 | C31: =报关资料录入!E53 -> 0 | F31: =报关资料录入!J53 -> 1 | G31: =报关资料录入!K53 -> 个 | H31: =报关资料录入!L53 -> 0 | I31: USD | J31: =H31*F31 -> 0
B32: =报关资料录入!B55 -> 18 | C32: =报关资料录入!E55 -> 0 | F32: =报关资料录入!J55 -> 1 | G32: =报关资料录入!K55 -> 个 | H32: =报关资料录入!L55 -> 0 | I32: USD | J32: =H32*F32 -> 0
B33: =报关资料录入!B57 -> 19 | C33: =报关资料录入!E57 -> 0 | F33: =报关资料录入!J57 -> 1 | G33: =报关资料录入!K57 -> 个 | H33: =报关资料录入!L57 -> 0 | I33: USD | J33: =H33*F33 -> 0
B34: =报关资料录入!B59 -> 20 | C34: =报关资料录入!E59 -> 0 | F34: =报关资料录入!J59 -> 1 | G34: =报关资料录入!K59 -> 个 | H34: =报关资料录入!L59 -> 0 | I34: USD | J34: =H34*F34 -> 0
B35: =报关资料录入!B61 -> 21 | C35: =报关资料录入!E61 -> 0 | F35: =报关资料录入!J61 -> 1 | G35: =报关资料录入!K61 -> 个 | H35: =报关资料录入!L61 -> 0 | I35: USD | J35: =H35*F35 -> 0
B36: =报关资料录入!B63 -> 22 | C36: =报关资料录入!E63 -> 0 | F36: =报关资料录入!J63 -> 1 | G36: =报关资料录入!K63 -> 个 | H36: =报关资料录入!L63 -> 0 | I36: USD | J36: =H36*F36 -> 0
B37: =报关资料录入!B65 -> 23 | C37: =报关资料录入!E65 -> 0 | F37: =报关资料录入!J65 -> 1 | G37: =报关资料录入!K65 -> 个 | H37: =报关资料录入!L65 -> 0 | I37: USD | J37: =H37*F37 -> 0
B38: =报关资料录入!B67 -> 24 | C38: =报关资料录入!E67 -> 0 | F38: =报关资料录入!J67 -> 1 | G38: =报关资料录入!K66 -> 0 | H38: =报关资料录入!L67 -> 0 | I38: USD | J38: =H38*F38 -> 0
B39: =报关资料录入!B69 -> 25 | C39: =报关资料录入!E69 -> 0 | F39: =报关资料录入!J69 -> 1 | G39: =报关资料录入!K67 -> 个 | H39: =报关资料录入!L69 -> 0 | I39: USD | J39: =H39*F39 -> 0
B40: =报关资料录入!B71 -> 26 | C40: =报关资料录入!E71 -> 0 | F40: =报关资料录入!J71 -> 1 | G40: =报关资料录入!K68 -> 0 | H40: =报关资料录入!L71 -> 0 | I40: USD | J40: =H40*F40 -> 0
B41: =报关资料录入!B73 -> 27 | C41: =报关资料录入!E73 -> 0 | F41: =报关资料录入!J73 -> 1 | G41: =报关资料录入!K69 -> 个 | H41: =报关资料录入!L73 -> 0 | I41: USD | J41: =H41*F41 -> 0
B42: =报关资料录入!B75 -> 28 | C42: =报关资料录入!E75 -> 0 | F42: =报关资料录入!J75 -> 1 | G42: =报关资料录入!K70 -> 0 | H42: =报关资料录入!L75 -> 0 | I42: USD | J42: =H42*F42 -> 0
B43: =报关资料录入!B77 -> 29 | C43: =报关资料录入!E77 -> 0 | F43: =报关资料录入!J77 -> 1 | G43: =报关资料录入!K71 -> 个 | H43: =报关资料录入!L77 -> 0 | I43: USD | J43: =H43*F43 -> 0
B44: =报关资料录入!B79 -> 30 | C44: =报关资料录入!E79 -> 0 | F44: =报关资料录入!J79 -> 1 | G44: =报关资料录入!K72 -> 0 | H44: =报关资料录入!L79 -> 0 | I44: USD | J44: =H44*F44 -> 0
B45: ="合计"&报关单!K22&":" -> 合计美元 : | D45: =IF(J45="","",IF(INT(J45)-J45=0,TEXT(INT(J45),"[dbnum2]")&"元整",IF(INT(J45*100)-INT(J45*10)*10=0,TEXT(INT(J45),"[dbnum2]")&"元"&TEXT(MID(J45,SEARCHB(".",J45,1)+1,1),"[dbnum2]")&"角整",IF(INT(J45*10)-INT(J45)*10=0,TEXT(INT(J45),"[dbnum2]")&"元"&"零"&TEXT(MID(J45,SEARCHB(".",J45,1)+2,1),"[dbnum2]")&"分",TEXT(INT(J45),"[dbnum2]")&"元"&TEXT(MID(J45,SEARCHB(".",J45,1)+1,1),"[dbnum2]")&"角"&TEXT(MID(J45,SEARCHB(".",J45,1)+2,1),"[dbnum2]")&"分")))) -> 零元整 | H45: TOTAL : | I45: =报关资料录入!K15 -> USD | J45: =SUM(J15:J44) -> 0
B48: 唛头 Marks:
B50: =报关资料录入!H16 -> N/M

Sheet 合同
B2: 合 同
B3: CONTRACT
B5: 卖 方 Sellers : | D5: =报关资料录入!E4 -> 深圳市沐星科技有限公司 | I5: 合同号 : | J5: =报关资料录入!K9 -> HS-US-20260312
B6: 地 址 Address : | D6: =报关资料录入!E7 -> 深圳市龙岗区龙城街道黄阁坑社区吉祥里豪庭9栋铭德大厦A、B栋A座1010 | I6: Contract No :
B7: 电话 Tel.： | E7: 传真 Fax : | I7: 签约日期 : | J7: =报关资料录入!K10 -> 46093
I8: Date :
B9: 买 方 Buyers : | D9: =报关资料录入!H4 -> HONG KONG HENGSHUO INTELLIGENT TECHNOLOGY CO., LIMITED | I9: 签约地点 : | J9: =报关资料录入!K11 -> 深圳
B10: 地 址 Address : | D10: =报关资料录入!H5 -> WORKSHOP 60, 3/F, BLOCK A, EAST SUN INDUSTRIAL CENTRE NO.16, SHING YIP STREET KL | I10: Signed at :
B12: 电话 Tel.： | E12: 传真 Fax :
B14: 经买卖双方确认根据下列条款订立本合同：
B15: This contract is made out by the Sellers and Buyers as per the following terms and conditions mutually confirmed:
B17: 项号 No. | C17: (1) 商品名称及规格 Description of Goods | F17: (2) 数量/重量 Quantity/Weight | H17: (3) 单价 Unit price | I17: (4) 总金额 Amount
B19: =报关资料录入!B21 -> 1 | C19: =报关资料录入!E21 -> 0 | F19: =报关资料录入!J21 -> 1 | G19: =报关资料录入!K21 -> 个 | H19: =报关资料录入!L21 -> 0 | I19: =报关资料录入!K15 -> USD | J19: =H19*F19 -> 0
B20: =报关资料录入!B23 -> 2 | C20: =报关资料录入!E23 -> 0 | F20: =报关资料录入!J23 -> 1 | G20: =报关资料录入!K23 -> 个 | H20: =报关资料录入!L23 -> 0 | I20: =I19 -> USD | J20: =H20*F20 -> 0
B21: =报关资料录入!B25 -> 3 | C21: =报关资料录入!E25 -> 0 | F21: =报关资料录入!J25 -> 1 | G21: =报关资料录入!K25 -> 个 | H21: =报关资料录入!L25 -> 0 | I21: =I20 -> USD | J21: =H21*F21 -> 0
B22: =报关资料录入!B27 -> 4 | C22: =报关资料录入!E27 -> 0 | F22: =报关资料录入!J27 -> 1 | G22: =报关资料录入!K27 -> 个 | H22: =报关资料录入!L27 -> 0 | I22: =I21 -> USD | J22: =H22*F22 -> 0
B23: =报关资料录入!B29 -> 5 | C23: =报关资料录入!E29 -> 0 | F23: =报关资料录入!J29 -> 1 | G23: =报关资料录入!K29 -> 个 | H23: =报关资料录入!L29 -> 0 | I23: =I22 -> USD | J23: =H23*F23 -> 0
B24: =报关资料录入!B31 -> 6 | C24: =报关资料录入!E31 -> 0 | F24: =报关资料录入!J31 -> 1 | G24: =报关资料录入!K31 -> 个 | H24: =报关资料录入!L31 -> 0 | I24: =I23 -> USD | J24: =H24*F24 -> 0
B25: =报关资料录入!B33 -> 7 | C25: =报关资料录入!E33 -> 0 | F25: =报关资料录入!J33 -> 1 | G25: =报关资料录入!K33 -> 个 | H25: =报关资料录入!L33 -> 0 | I25: =I24 -> USD | J25: =H25*F25 -> 0
B26: =报关资料录入!B35 -> 8 | C26: =报关资料录入!E35 -> 0 | F26: =报关资料录入!J35 -> 1 | G26: =报关资料录入!K35 -> 个 | H26: =报关资料录入!L35 -> 0 | I26: =I25 -> USD | J26: =H26*F26 -> 0
B27: =报关资料录入!B37 -> 9 | C27: =报关资料录入!E37 -> 0 | F27: =报关资料录入!J37 -> 1 | G27: =报关资料录入!K37 -> 个 | H27: =报关资料录入!L37 -> 0 | I27: =I26 -> USD | J27: =H27*F27 -> 0
B28: =报关资料录入!B39 -> 10 | C28: =报关资料录入!E39 -> 0 | F28: =报关资料录入!J39 -> 1 | G28: =报关资料录入!K39 -> 个 | H28: =报关资料录入!L39 -> 0 | I28: =I27 -> USD | J28: =H28*F28 -> 0
B29: =报关资料录入!B41 -> 11 | C29: =报关资料录入!E41 -> 0 | F29: =报关资料录入!J41 -> 1 | G29: =报关资料录入!K41 -> 个 | H29: =报关资料录入!L41 -> 0 | I29: =I28 -> USD | J29: =H29*F29 -> 0
B30: =报关资料录入!B43 -> 12 | C30: =报关资料录入!E43 -> 0 | F30: =报关资料录入!J43 -> 1 | G30: =报关资料录入!K43 -> 个 | H30: =报关资料录入!L43 -> 0 | I30: =I29 -> USD | J30: =H30*F30 -> 0
B31: =报关资料录入!B45 -> 13 | C31: =报关资料录入!E45 -> 0 | F31: =报关资料录入!J45 -> 1 | G31: =报关资料录入!K45 -> 个 | H31: =报关资料录入!L45 -> 0 | I31: =I30 -> USD | J31: =H31*F31 -> 0
B32: =报关资料录入!B47 -> 14 | C32: =报关资料录入!E47 -> 0 | F32: =报关资料录入!J47 -> 1 | G32: =报关资料录入!K47 -> 个 | H32: =报关资料录入!L47 -> 0 | I32: =I31 -> USD | J32: =H32*F32 -> 0
B33: =报关资料录入!B49 -> 15 | C33: =报关资料录入!E49 -> 0 | F33: =报关资料录入!J49 -> 1 | G33: =报关资料录入!K49 -> 个 | H33: =报关资料录入!L49 -> 0 | I33: =I32 -> USD | J33: =H33*F33 -> 0
B34: =报关资料录入!B51 -> 16 | C34: =报关资料录入!E51 -> 0 | F34: =报关资料录入!J51 -> 1 | G34: =报关资料录入!K51 -> 个 | H34: =报关资料录入!L51 -> 0 | I34: =I33 -> USD | J34: =H34*F34 -> 0
B35: =报关资料录入!B53 -> 17 | C35: =报关资料录入!E53 -> 0 | F35: =报关资料录入!J53 -> 1 | G35: =报关资料录入!K53 -> 个 | H35: =报关资料录入!L53 -> 0 | I35: =I34 -> USD | J35: =H35*F35 -> 0
B36: =报关资料录入!B55 -> 18 | C36: =报关资料录入!E55 -> 0 | F36: =报关资料录入!J55 -> 1 | G36: =报关资料录入!K55 -> 个 | H36: =报关资料录入!L55 -> 0 | I36: =I35 -> USD | J36: =H36*F36 -> 0
B37: =报关资料录入!B57 -> 19 | C37: =报关资料录入!E57 -> 0 | F37: =报关资料录入!J57 -> 1 | G37: =报关资料录入!K57 -> 个 | H37: =报关资料录入!L57 -> 0 | I37: =I36 -> USD | J37: =H37*F37 -> 0
B38: =报关资料录入!B59 -> 20 | C38: =报关资料录入!E59 -> 0 | F38: =报关资料录入!J59 -> 1 | G38: =报关资料录入!K59 -> 个 | H38: =报关资料录入!L59 -> 0 | I38: =I37 -> USD | J38: =H38*F38 -> 0
B39: =报关资料录入!B61 -> 21 | C39: =报关资料录入!E61 -> 0 | F39: =报关资料录入!J61 -> 1 | G39: =报关资料录入!K61 -> 个 | H39: =报关资料录入!L61 -> 0 | I39: =I38 -> USD | J39: =H39*F39 -> 0
B40: =报关资料录入!B63 -> 22 | C40: =报关资料录入!E63 -> 0 | F40: =报关资料录入!J63 -> 1 | G40: =报关资料录入!K63 -> 个 | H40: =报关资料录入!L63 -> 0 | I40: =I39 -> USD | J40: =H40*F40 -> 0
B41: =报关资料录入!B65 -> 23 | C41: =报关资料录入!E65 -> 0 | F41: =报关资料录入!J65 -> 1 | G41: =报关资料录入!K65 -> 个 | H41: =报关资料录入!L65 -> 0 | I41: =I40 -> USD | J41: =H41*F41 -> 0
B42: =报关资料录入!B67 -> 24 | C42: =报关资料录入!E67 -> 0 | F42: =报关资料录入!J67 -> 1 | G42: =报关资料录入!K67 -> 个 | H42: =报关资料录入!L67 -> 0 | I42: =I41 -> USD | J42: =H42*F42 -> 0
B43: =报关资料录入!B69 -> 25 | C43: =报关资料录入!E69 -> 0 | F43: =报关资料录入!J69 -> 1 | G43: =报关资料录入!K69 -> 个 | H43: =报关资料录入!L69 -> 0 | I43: =I42 -> USD | J43: =H43*F43 -> 0
B44: =报关资料录入!B71 -> 26 | C44: =报关资料录入!E71 -> 0 | F44: =报关资料录入!J71 -> 1 | G44: =报关资料录入!K71 -> 个 | H44: =报关资料录入!L71 -> 0 | I44: =I43 -> USD | J44: =H44*F44 -> 0
B45: =报关资料录入!B73 -> 27 | C45: =报关资料录入!E73 -> 0 | F45: =报关资料录入!J73 -> 1 | G45: =报关资料录入!K73 -> 个 | H45: =报关资料录入!L73 -> 0 | I45: =I44 -> USD | J45: =H45*F45 -> 0
B46: =报关资料录入!B75 -> 28 | C46: =报关资料录入!E75 -> 0 | F46: =报关资料录入!J75 -> 1 | G46: =报关资料录入!K75 -> 个 | H46: =报关资料录入!L75 -> 0 | I46: =I45 -> USD | J46: =H46*F46 -> 0
B47: =报关资料录入!B77 -> 29 | C47: =报关资料录入!E77 -> 0 | F47: =报关资料录入!J77 -> 1 | G47: =报关资料录入!K77 -> 个 | H47: =报关资料录入!L77 -> 0 | I47: =I46 -> USD | J47: =H47*F47 -> 0
B48: =报关资料录入!B79 -> 30 | C48: =报关资料录入!E79 -> 0 | F48: =报关资料录入!J79 -> 1 | G48: =报关资料录入!K79 -> 个 | H48: =报关资料录入!L79 -> 0 | I48: =I47 -> USD | J48: =H48*F48 -> 0
B49: TOTAL : | I49: =报关资料录入!K15 -> USD | J49: =SUM(J19:J48) -> 0
B51: 总值(大写) Total Amount: | E51: =IF(J49="","",IF(INT(J49)-J49=0,TEXT(INT(J49),"[dbnum2]")&"元整",IF(INT(J49*100)-INT(J49*10)*10=0,TEXT(INT(J49),"[dbnum2]")&"元"&TEXT(MID(J49,SEARCHB(".",J49,1)+1,1),"[dbnum2]")&"角整",IF(INT(J49*10)-INT(J49)*10=0,TEXT(INT(J49),"[dbnum2]")&"元"&"零"&TEXT(MID(J49,SEARCHB(".",J49,1)+2,1),"[dbnum2]")&"分",TEXT(INT(J49),"[dbnum2]")&"元"&TEXT(MID(J49,SEARCHB(".",J49,1)+1,1),"[dbnum2]")&"角"&TEXT(MID(J49,SEARCHB(".",J49,1)+2,1),"[dbnum2]")&"分")))) -> 零元整
B54: 数量及总价允许有 5 %的增减。
B55: 5%more or less both in amount and quantity allowed.
B56: （5）成交方式： | D56: =报关资料录入!K14&报关资料录入!K11 -> FOB深圳
B57: （6）包装：按卖方一般出口包装。
B58: Packing: According to Seller's export worthy packaging.
B59: （7）装 运 期： | D59: 30天内
B60: Time of Shipment:
B61: Packing: According to Seller's export worthy packaging.
B62: （8）装运口岸及目的地： | E62: =装箱单!D10 -> 由 深圳 至 美国 | G62: 准许分批与转船。
B63: Loading Port & Destination: From | F63: with transshipment and partial shipments allowed.
B64: （9）保 险：由买方按发票总值加10%海运投保一切险及战争险，不保罢工险。按照中国人民保险公司
B65: 海洋运输货物保险条款进行投保。
B66: （10）其他 Others:
D68: 卖方 | H68: 买方
D69: The Sellers: | H69: The Buyers:

Sheet 存仓委托书
A2: 存仓委托书
B4: 公司:
B5: 我公司拟将下列货物存入贵公司出口监管仓库，这批货物属:
B6: R 一般贸易出口 £ 加工贸易企业出口
B7: 货物名称: | C7: =报关资料录入!E21 -> 0
B8: 境内货源地: | C8: =报关资料录入!K12 -> 深圳特区
B9: 规格及包装: | C9: =报关资料录入!H14 -> 纸制或纤维板制盒/箱
B10: 数 量: | C10: =装箱单!E77 -> 30 | E10: 件
B11: 重 量: | C11: =装箱单!H77 -> 30 | E11: 千克
B12: 价 值: | C12: =发票!I45 -> USD | D12: =发票!J45 -> 0
B13: 运输工具: | C13: =报关资料录入!E14 -> 水路运输
B14: 出境口岸: | C14: =报关资料录入!E10 -> 0
B15: 存 放 期: | C15: 一个月
B16: 请即与海关联系,准予办理货物入仓手续。
B19: 特此委托
B22: 申请人地址: | C22: =报关资料录入!E7 -> 深圳市龙岗区龙城街道黄阁坑社区吉祥里豪庭9栋铭德大厦A、B栋A座1010 | H22: 审请人签署：
B23: 电 话: | C23: =报关资料录入!E8 -> 0 | H23: （盖章）
B24: 传 真: | C24: =报关资料录入!F8 -> 0 | H24: =报关资料录入!G3 -> 46115

Sheet 申报要素
B2: 货 物 申 报 要 素 表
C3: S/O号码：
B5: 序号 | C5: 货物品名 | D5: 商品编码 | E5: 申报要素描述
B6: =报关资料录入!B21 -> 1 | C6: =报关资料录入!E21 -> 0 | D6: =报关资料录入!C21 -> 0 | E6: =报关资料录入!E22 -> 0
B7: =报关资料录入!B23 -> 2 | C7: =报关资料录入!E23 -> 0 | D7: =报关资料录入!C23 -> 0 | E7: =报关资料录入!E24 -> 0
B8: =报关资料录入!B25 -> 3 | C8: =报关资料录入!E25 -> 0 | D8: =报关资料录入!C25 -> 0 | E8: =报关资料录入!E26 -> 0
B9: =报关资料录入!B27 -> 4 | C9: =报关资料录入!E27 -> 0 | D9: =报关资料录入!C27 -> 0 | E9: =报关资料录入!E28 -> 0
B10: =报关资料录入!B29 -> 5 | C10: =报关资料录入!E29 -> 0 | D10: =报关资料录入!C29 -> 0 | E10: =报关资料录入!E30 -> 0
B11: =报关资料录入!B31 -> 6 | C11: =报关资料录入!E31 -> 0 | D11: =报关资料录入!C31 -> 0 | E11: =报关资料录入!E32 -> 0
B12: =报关资料录入!B33 -> 7 | C12: =报关资料录入!E33 -> 0 | D12: =报关资料录入!C33 -> 0 | E12: =报关资料录入!E34 -> 0
B13: =报关资料录入!B35 -> 8 | C13: =报关资料录入!E35 -> 0 | D13: =报关资料录入!C35 -> 0 | E13: =报关资料录入!E36 -> 0
B14: =报关资料录入!B37 -> 9 | C14: =报关资料录入!E37 -> 0 | D14: =报关资料录入!C37 -> 0 | E14: =报关资料录入!E38 -> 0
B15: =报关资料录入!B39 -> 10 | C15: =报关资料录入!E39 -> 0 | D15: =报关资料录入!C39 -> 0 | E15: =报关资料录入!E40 -> 0
B16: =报关资料录入!B41 -> 11 | C16: =报关资料录入!E41 -> 0 | D16: =报关资料录入!C41 -> 0 | E16: =报关资料录入!E42 -> 0
B17: =报关资料录入!B43 -> 12 | C17: =报关资料录入!E43 -> 0 | D17: =报关资料录入!C43 -> 0 | E17: =报关资料录入!E44 -> 0
B18: =报关资料录入!B45 -> 13 | C18: =报关资料录入!E45 -> 0 | D18: =报关资料录入!C45 -> 0 | E18: =报关资料录入!E46 -> 0
B19: =报关资料录入!B47 -> 14 | C19: =报关资料录入!E47 -> 0 | D19: =报关资料录入!C47 -> 0 | E19: =报关资料录入!E48 -> 0
B20: =报关资料录入!B49 -> 15 | C20: =报关资料录入!E49 -> 0 | D20: =报关资料录入!C49 -> 0 | E20: =报关资料录入!E50 -> 0
B21: =报关资料录入!B51 -> 16 | C21: =报关资料录入!E51 -> 0 | D21: =报关资料录入!C51 -> 0 | E21: =报关资料录入!E52 -> 0
B22: =报关资料录入!B53 -> 17 | C22: =报关资料录入!E53 -> 0 | D22: =报关资料录入!C53 -> 0 | E22: =报关资料录入!E54 -> 0
B23: =报关资料录入!B55 -> 18 | C23: =报关资料录入!E55 -> 0 | D23: =报关资料录入!C55 -> 0 | E23: =报关资料录入!E56 -> 0
B24: =报关资料录入!B57 -> 19 | C24: =报关资料录入!E57 -> 0 | D24: =报关资料录入!C57 -> 0 | E24: =报关资料录入!E58 -> 0
B25: =报关资料录入!B59 -> 20 | C25: =报关资料录入!E59 -> 0 | D25: =报关资料录入!C59 -> 0 | E25: =报关资料录入!E60 -> 0
B26: =报关资料录入!B61 -> 21 | C26: =报关资料录入!E61 -> 0 | D26: =报关资料录入!C61 -> 0 | E26: =报关资料录入!E62 -> 0
B27: =报关资料录入!B63 -> 22 | C27: =报关资料录入!E63 -> 0 | D27: =报关资料录入!C63 -> 0 | E27: =报关资料录入!E64 -> 0
B28: =报关资料录入!B65 -> 23 | C28: =报关资料录入!E65 -> 0 | D28: =报关资料录入!C65 -> 0 | E28: =报关资料录入!E66 -> 0
B29: =报关资料录入!B67 -> 24 | C29: =报关资料录入!E67 -> 0 | D29: =报关资料录入!C67 -> 0 | E29: =报关资料录入!E68 -> 0
B30: =报关资料录入!B69 -> 25 | C30: =报关资料录入!E69 -> 0 | D30: =报关资料录入!C69 -> 0 | E30: =报关资料录入!E70 -> 0
B31: =报关资料录入!B71 -> 26 | C31: =报关资料录入!E71 -> 0 | D31: =报关资料录入!C71 -> 0 | E31: =报关资料录入!E72 -> 0
B32: =报关资料录入!B73 -> 27 | C32: =报关资料录入!E73 -> 0 | D32: =报关资料录入!C73 -> 0 | E32: =报关资料录入!E74 -> 0
B33: =报关资料录入!B75 -> 28 | C33: =报关资料录入!E75 -> 0 | D33: =报关资料录入!C75 -> 0 | E33: =报关资料录入!E76 -> 0
B34: =报关资料录入!B77 -> 29 | C34: =报关资料录入!E77 -> 0 | D34: =报关资料录入!C77 -> 0 | E34: =报关资料录入!E78 -> 0
B35: =报关资料录入!B79 -> 30 | C35: =报关资料录入!E79 -> 0 | D35: =报关资料录入!C79 -> 0 | E35: =报关资料录入!E80 -> 0

Sheet 报关委托书
A1: 代 理 报 关 委 托 书
F3: 编号：002 | G3: =RAND()*17560351+35308767 -> 50665779
B4: :
A5: 我单位现 (A逐票、B长期)委托贵公司代理 等通关事宜。（A、报关查验 B、辅助查验 C、
A6: 垫缴税款 D、办理海关证明联 E、审批手册 F、核销手册 G、申办减免税手续 H、其他 ）详见《委托
A7: 报关协议》。
A8: 我单位保证遵守《海关法》和国家有关法规，保证所提供的情况真实、完整、单货相符。否则，愿
A9: 承担相关法律责任。
A10: =F14+30 -> 46145
E11: 委托方（盖章）：
C13: 法定代表人或其授权签署《代理报关委托书》的人（签字）
F14: =报关资料录入!G3 -> 46115
D15: 委 托 报 关 协 议
A16: 为明确委托报关具体事项和各自责任，双方经平等协商签定协议如下：
A17: 委托方 | B17: =报关资料录入!E4 -> 深圳市沐星科技有限公司 | E17: 被委托方 | F17: =报关资料录入!I3 -> 0
A18: 主要货物名称 | B18: =报关资料录入!E21 -> 0 | E18: *报关单编码 | F18: No.
A19: HS编码 | B19: =报关资料录入!C21 -> 0 | E19: 收到单证日期 | F19: 年 月 日
A20: 货物总价 | B20: =发票!I45 -> USD | C20: =发票!J45 -> 0 | E20: 收到单证情况 | F20: 合同R | G20: 发票R
A21: 进出口日期 | B21: =IF(报关单!J5>0,报关单!J5,"年 月 日") -> 年 月 日 | F21: 装箱清单R | G21: 提（运）单£
A22: 提单号 | B22: =报关资料录入!E16 -> 0 | F22: 加工贸易手册£ | G22: 许可证件£
A23: 贸易方式 | B23: =报关资料录入!H9 -> 一般贸易 | F23: 其他
A24: 原产地/货源地 | B24: =报关资料录入!K12 -> 深圳特区 | E24: 报关则费 | F24: 人民币： | G24: 元
A25: 其他要求： | E25: 承诺说明：
A27: 背面所列通用条款是本协议不可分割的一部分，对本协议的签署构成了对背面通用条款的同意。 | E27: 背面所列通用条款是本协议不可分割的一部分，对本协议的签署构成了对背面通用条款的同意。
A28: 委托方业务签章： | E28: 被委托方业务签章：
A30: 经办人签章： | B30: =报关资料录入!D3 -> 0 | E30: 经办报关员签章：
A31: 联系电话： | B31: =报关资料录入!E3 -> 0 | E31: 联系电话：
B32: =F14 -> 46115 | F32: 年 月 日
D34: （白联：海关留存、黄联：被委托方留存、红联：委托方留存） | G34: 中国报关协会监制
